pyntegrity/__init__.py
pyntegrity/__main__.py
pyntegrity/config.py
pyntegrity/core.py
pyntegrity/exceptions.py
pyntegrity-1.3.0.dist-info/LICENSE
pyntegrity-1.3.0.dist-info/METADATA
pyntegrity-1.3.0.dist-info/WHEEL
pyntegrity-1.3.0.dist-info/top_level.txt
pyntegrity-1.3.0.dist-info/RECORD
