Metadata-Version: 2.1
Name: pyntegrity
Version: 1.3.0
Summary: Pyntegrity is a Python package that helps you check a file integrity.
Home-page: https://github.com/ddalu5/pyntegrity
Author: Salah OSFOR
Author-email: osfor.salah@gmail.com
License: GPL-3.0
Platform: UNKNOWN
Classifier: Intended Audience :: Developers
Classifier: Intended Audience :: System Administrators
Classifier: Intended Audience :: Information Technology
Classifier: Topic :: Security
Classifier: Programming Language :: Python :: 3.7
Classifier: Programming Language :: Python :: 3.8
Classifier: Programming Language :: Python :: 3.9
Classifier: Programming Language :: Python :: 3.10
License-File: LICENSE
